blatann/__init__.py
blatann/device.py
blatann/event_args.py
blatann/event_type.py
blatann/exceptions.py
blatann/peer.py
blatann/uuid.py
blatann/bt_sig/__init__.py
blatann/bt_sig/assigned_numbers.py
blatann/bt_sig/uuids.py
blatann/examples/__init__.py
blatann/examples/__main__.py
blatann/examples/broadcaster.py
blatann/examples/central.py
blatann/examples/central_async.py
blatann/examples/central_battery_service.py
blatann/examples/central_descriptors.py
blatann/examples/central_device_info_service.py
blatann/examples/central_event_driven.py
blatann/examples/central_uart_service.py
blatann/examples/constants.py
blatann/examples/example_utils.py
blatann/examples/peripheral.py
blatann/examples/peripheral_async.py
blatann/examples/peripheral_battery_service.py
blatann/examples/peripheral_current_time_service.py
blatann/examples/peripheral_descriptors.py
blatann/examples/peripheral_device_info_service.py
blatann/examples/peripheral_glucose_service.py
blatann/examples/peripheral_rssi.py
blatann/examples/peripheral_uart_service.py
blatann/examples/scanner.py
blatann/examples/scanner_async.py
blatann/gap/__init__.py
blatann/gap/advertise_data.py
blatann/gap/advertising.py
blatann/gap/bond_db.py
blatann/gap/default_bond_db.py
blatann/gap/gap_types.py
blatann/gap/generic_access_service.py
blatann/gap/scanning.py
blatann/gap/smp.py
blatann/gap/smp_crypto.py
blatann/gap/smp_types.py
blatann/gatt/__init__.py
blatann/gatt/gattc.py
blatann/gatt/gattc_attribute.py
blatann/gatt/gatts.py
blatann/gatt/gatts_attribute.py
blatann/gatt/managers.py
blatann/gatt/reader.py
blatann/gatt/service_discovery.py
blatann/gatt/writer.py
blatann/nrf/__init__.py
blatann/nrf/nrf_dll_load.py
blatann/nrf/nrf_driver.py
blatann/nrf/nrf_driver_types.py
blatann/nrf/nrf_events/__init__.py
blatann/nrf/nrf_events/gap_events.py
blatann/nrf/nrf_events/gatt_events.py
blatann/nrf/nrf_events/generic_events.py
blatann/nrf/nrf_events/smp_events.py
blatann/nrf/nrf_types/__init__.py
blatann/nrf/nrf_types/config.py
blatann-0.6.0.dist-info/LICENSE
blatann-0.6.0.dist-info/METADATA
blatann-0.6.0.dist-info/WHEEL
blatann-0.6.0.dist-info/top_level.txt
blatann-0.6.0.dist-info/RECORD
