Metadata-Version: 2.1
Name: blatann
Version: 0.6.0
Summary: Python BLE library for using Nordic nRF52 with Connectivity firmware
Author-email: Thomas Gerstenberg <tgerst6@gmail.com>
License: BSD 3-Clause
Project-URL: Documentation, https://blatann.readthedocs.io/en/latest/
Project-URL: Repository, https://github.com/ThomasGerstenberg/blatann
Project-URL: Changelog, https://blatann.readthedocs.io/en/latest/changelog.html
Keywords: ble,bluetooth,nrf52,nordic
Classifier: Programming Language :: Python :: 3
Classifier: License :: OSI Approved :: BSD License
Classifier: Operating System :: OS Independent
Requires-Python: >=3.7
License-File: LICENSE
Requires-Dist: pc-ble-driver-py >=0.13
Requires-Dist: cryptography
Requires-Dist: pytz
Provides-Extra: dev
Requires-Dist: build ; extra == 'dev'
Requires-Dist: ruff ; extra == 'dev'
Requires-Dist: isort ; extra == 'dev'
